Metadata-Version: 2.1
Name: setup-generator
Version: 1.0
Summary: Pequena biblioteca para criar um setup.py rápido.
Home-page: https://github.com/Hoyasumii/SetupGenerator
Author: Alan Reis Anjos
Author-email: alanreisanjo@gmail.com
License: GPL-3.0
License-File: LICENSE
Requires-Dist: Jinja2==3.1.2
Requires-Dist: keyboard==0.13.5
Requires-Dist: MarkupSafe==2.1.3
Requires-Dist: python-slugify==8.0.1
Requires-Dist: setuptools==69.0.3
Requires-Dist: simple-form==1.0
Requires-Dist: text-unidecode==1.3
